egs_api/__init__.py
egs_api/epic_games.py
egs_api/api/__init__.py
egs_api/api/account.py
egs_api/api/egs.py
egs_api/api/epic_api.py
egs_api/api/error.py
egs_api/api/fab.py
egs_api/api/login.py
egs_api/api/types/__init__.py
egs_api/api/types/account.py
egs_api/api/types/asset_info.py
egs_api/api/types/asset_manifest.py
egs_api/api/types/download_manifest.py
egs_api/api/types/entitlement.py
egs_api/api/types/epic_asset.py
egs_api/api/types/fab_asset_manifest.py
egs_api/api/types/fab_library.py
egs_api/api/types/friends.py
egs_api/api/types/library.py
egs_api_py-1.0.0.dist-info/licenses/LICENSE
egs_api_py-1.0.0.dist-info/METADATA
egs_api_py-1.0.0.dist-info/WHEEL
egs_api_py-1.0.0.dist-info/top_level.txt
egs_api_py-1.0.0.dist-info/RECORD
