Metadata-Version: 2.4
Name: egs-api-py
Version: 1.0.0
Summary: A minimal asynchronous interface to Epic Games Store in python new FAB marketplace API.
Home-page: https://github.com/LaurentOngaro/egs-api-py
Author: Laurent Ongaro
Author-email: laurent@gameamea.com
License: MIT
Classifier: License :: OSI Approved :: MIT License
Classifier: Programming Language :: Python :: 3.9
Classifier: Programming Language :: Python :: 3.10
Classifier: Programming Language :: Python :: 3.11
Classifier: Programming Language :: Python :: 3.12
Classifier: Operating System :: OS Independent
Classifier: Development Status :: 5 - Production/Stable
Requires-Python: >=3.9
License-File: LICENSE
Dynamic: author
Dynamic: author-email
Dynamic: classifier
Dynamic: description
Dynamic: description-content-type
Dynamic: home-page
Dynamic: license
Dynamic: license-file
Dynamic: requires-python
Dynamic: summary
